collective.behavior.relatedmedia-3.5.3-py3.11-nspkg.pth
collective/behavior/relatedmedia/__init__.py
collective/behavior/relatedmedia/behavior.py
collective/behavior/relatedmedia/browser.py
collective/behavior/relatedmedia/configure.zcml
collective/behavior/relatedmedia/events.py
collective/behavior/relatedmedia/interfaces.py
collective/behavior/relatedmedia/related_attachments.pt
collective/behavior/relatedmedia/related_images.pt
collective/behavior/relatedmedia/testing.py
collective/behavior/relatedmedia/transform.py
collective/behavior/relatedmedia/upgrades.py
collective/behavior/relatedmedia/upgrades.zcml
collective/behavior/relatedmedia/utils.py
collective/behavior/relatedmedia/viewlet_uploader.pt
collective/behavior/relatedmedia/widget.py
collective/behavior/relatedmedia/widget_attachments_display.pt
collective/behavior/relatedmedia/widget_images_display.pt
collective/behavior/relatedmedia/locales/collective.behavior.relatedmedia.pot
collective/behavior/relatedmedia/locales/update.sh
collective/behavior/relatedmedia/locales/de/LC_MESSAGES/collective.behavior.relatedmedia.mo
collective/behavior/relatedmedia/locales/de/LC_MESSAGES/collective.behavior.relatedmedia.po
collective/behavior/relatedmedia/locales/en/LC_MESSAGES/collective.behavior.relatedmedia.mo
collective/behavior/relatedmedia/locales/en/LC_MESSAGES/collective.behavior.relatedmedia.po
collective/behavior/relatedmedia/profiles/default/browserlayer.xml
collective/behavior/relatedmedia/profiles/default/controlpanel.xml
collective/behavior/relatedmedia/profiles/default/metadata.xml
collective/behavior/relatedmedia/profiles/default/registry.xml
collective/behavior/relatedmedia/profiles/default/types/Document.xml
collective/behavior/relatedmedia/profiles/uninstall/browserlayer.xml
collective/behavior/relatedmedia/profiles/uninstall/controlpanel.xml
collective/behavior/relatedmedia/profiles/uninstall/registry.xml
collective/behavior/relatedmedia/profiles/uninstall/types/Document.xml
collective.behavior.relatedmedia-3.5.3.dist-info/METADATA
collective.behavior.relatedmedia-3.5.3.dist-info/WHEEL
collective.behavior.relatedmedia-3.5.3.dist-info/entry_points.txt
collective.behavior.relatedmedia-3.5.3.dist-info/namespace_packages.txt
collective.behavior.relatedmedia-3.5.3.dist-info/top_level.txt
collective.behavior.relatedmedia-3.5.3.dist-info/RECORD
