Metadata-Version: 2.1
Name: collective.behavior.relatedmedia
Version: 3.5.3
Summary: Adds Various configuration fields and viewlets to manage and show content related images and attachments
Home-page: https://github.com/kombinat/collective.behavior.relatedmedia
Author: petschki
Author-email: peter.mathis@kombinat.at
License: gpl
Keywords: plone richmedia relatedmedia
Classifier: Development Status :: 5 - Production/Stable
Classifier: Framework :: Plone :: 6.0
Classifier: Framework :: Plone :: Addon
Classifier: Framework :: Plone
Classifier: License :: OSI Approved :: GNU General Public License v2 (GPLv2)
Classifier: Programming Language :: Python :: 3.8
Classifier: Programming Language :: Python :: 3.9
Classifier: Programming Language :: Python :: 3.10
Classifier: Programming Language :: Python :: 3.11
Classifier: Programming Language :: Python
Classifier: Topic :: Software Development :: Libraries :: Python Modules
Requires-Python: >=3.8
Requires-Dist: setuptools
Requires-Dist: plone.api
Requires-Dist: plone.behavior
Requires-Dist: plone.app.dexterity
Requires-Dist: Products.CMFCore
Requires-Dist: z3c.form
Provides-Extra: test
Requires-Dist: plone.app.testing[robot] ; extra == 'test'
Requires-Dist: plone.app.robotframework ; extra == 'test'
Requires-Dist: plone.app.contenttypes ; extra == 'test'
Requires-Dist: robotframework-selenium2library ; extra == 'test'
Requires-Dist: robotframework-selenium2screenshots ; extra == 'test'
